ai_service.py
app.py
cartRoutes.py
extensions.py
restaurantRoutes.py
run.py
run_app.py
vibe_eats_backend-0.3.post80.dist-info/METADATA
vibe_eats_backend-0.3.post80.dist-info/WHEEL
vibe_eats_backend-0.3.post80.dist-info/top_level.txt
vibe_eats_backend-0.3.post80.dist-info/RECORD
